scripts/example_executor.py
scripts/example_print_out_gpus.py
scripts/example_torch_run.py
submitit_tools/__init__.py
submitit_tools/configs/__init__.py
submitit_tools/configs/job_config.py
submitit_tools/configs/submitit_config.py
submitit_tools/jobs/__init__.py
submitit_tools/jobs/base_classes.py
submitit_tools/jobs/default_jobs.py
submitit_tools/jobs/run_state.py
submitit_tools/jobs/utils.py
submitit_tools-1.0.1.dist-info/METADATA
submitit_tools-1.0.1.dist-info/WHEEL
submitit_tools-1.0.1.dist-info/top_level.txt
submitit_tools-1.0.1.dist-info/RECORD
