Metadata-Version: 2.4
Name: submitit-tools
Version: 1.0.1
Summary: A package to manage slurm jobs on a HPC cluster
Author-email: Jacob Berg <jacob33@cs.washington.edu>
Project-URL: Repository, https://github.com/WEIRDLabUW/submitit-tools
Requires-Python: >=3.8
Requires-Dist: submitit
Requires-Dist: tqdm
Requires-Dist: wandb
Provides-Extra: torch
Requires-Dist: torch; extra == "torch"
Requires-Dist: torchvision; extra == "torch"
